uvraspy/__init__.py
uvraspy/main.py
uvraspy/bluetooth/BluetoothHandler.py
uvraspy/bluetooth/__init__.py
uvraspy/bluetooth/advertise.py
uvraspy/bluetooth/ble.py
uvraspy/bluetooth/const.py
uvraspy/bluetooth/service.py
uvraspy/calculator/__init__.py
uvraspy/calculator/uvcalculator.py
uvraspy/database/Alert.py
uvraspy/database/DataPoint.py
uvraspy/database/__init__.py
uvraspy/database/dbmanager.py
uvraspy/encryption/Cryptor.py
uvraspy/encryption/__init__.py
uvraspy/gather/HTSensor.py
uvraspy/gather/HTSensorTest.py
uvraspy/gather/PTSensorTest.py
uvraspy/gather/PTsensor.py
uvraspy/gather/UVsensor.py
uvraspy/gather/UVsensorTest.py
uvraspy/gather/__init__.py
uvraspy/gather/gather.py
uvraspy/preferences/__init__.py
uvraspy/preferences/preferences.py
uvraspy-1.0.5.dist-info/METADATA
uvraspy-1.0.5.dist-info/WHEEL
uvraspy-1.0.5.dist-info/entry_points.txt
uvraspy-1.0.5.dist-info/top_level.txt
uvraspy-1.0.5.dist-info/RECORD
