Metadata-Version: 2.1
Name: uvraspy
Version: 1.0.5
Summary: A Python package for Raspberry Pi
Home-page: UNKNOWN
Author: csM5-22-25
Author-email: n.aukes@student.utwente.nl
License: UNKNOWN
Keywords: python,RasPy,uvedora,pihat,fedora
Platform: UNKNOWN
Classifier: Development Status :: 4 - Beta
Classifier: Intended Audience :: End Users/Desktop
Classifier: Programming Language :: Python :: 3
Classifier: Operating System :: Unix
Requires-Dist: flake8
Requires-Dist: pytest
Requires-Dist: pytest-cov
Requires-Dist: pybluez
Requires-Dist: adafruit-blinka
Requires-Dist: adafruit-circuitpython-ltr390
Requires-Dist: adafruit-circuitpython-dht
Requires-Dist: pycryptodome
Requires-Dist: adafruit-circuitpython-bmp280
